README.rst
setup.py
upodder/__init__.py
upodder/upodder.py
upodder.egg-info/PKG-INFO
upodder.egg-info/SOURCES.txt
upodder.egg-info/dependency_links.txt
upodder.egg-info/entry_points.txt
upodder.egg-info/requires.txt
upodder.egg-info/top_level.txt
upodder/test/__init__.py
upodder/test/test_upodder.py