Metadata-Version: 1.1
Name: upodder
Version: 0.5.5
Summary: Command Line Podcast Downloader
Home-page: https://github.com/manuelRiel/upodder
Author: "Stan Vitkovskiy, Manuel Riel"
Author-email: stas.vitkovsky[at]gmail.com, manu[at]vlx.cc
License: LICENSE.txt
Platform: UNKNOWN
Classifier: Development Status :: 4 - Beta
Classifier: Environment :: Console
Classifier: Intended Audience :: End Users/Desktop
Classifier: License :: OSI Approved :: MIT License
Classifier: Operating System :: Unix
Classifier: Programming Language :: Python
Classifier: Programming Language :: Python :: 2.6
Classifier: Programming Language :: Python :: 2.7
Classifier: Programming Language :: Python :: 3
Classifier: Programming Language :: Python :: 3.3
Classifier: Programming Language :: Python :: 3.4
Classifier: Topic :: Internet :: WWW/HTTP :: Dynamic Content :: News/Diary
